lsys/__init__.py
lsys/algo.py
lsys/bezier.py
lsys/cli.py
lsys/fractals.py
lsys/lsys.py
lsys/validate.py
lsys/viz.py
lsys/tests/__init__.py
lsys/tests/test_algo.py
lsys/tests/test_bezier.py
lsys/tests/test_lsys.py
lsys/tests/test_validate.py
lsys/tests/test_viz.py
lsys-0.2.0.dist-info/AUTHORS.rst
lsys-0.2.0.dist-info/LICENSE
lsys-0.2.0.dist-info/METADATA
lsys-0.2.0.dist-info/WHEEL
lsys-0.2.0.dist-info/entry_points.txt
lsys-0.2.0.dist-info/top_level.txt
lsys-0.2.0.dist-info/RECORD
