Metadata-Version: 2.1
Name: lsys
Version: 0.2.0
Summary: Create and visualize Lindenmayer systems
Home-page: https://github.com/austinorr/lsys
Author: Austin Orr
Author-email: austinmartinorr@gmail.com
License: BSD license
Keywords: l-systems,lindenmayer,fractal
Classifier: Development Status :: 2 - Pre-Alpha
Classifier: Intended Audience :: Developers
Classifier: License :: OSI Approved :: BSD License
Classifier: Natural Language :: English
Classifier: Programming Language :: Python :: 3.6
Requires-Python: >=3.8
License-File: LICENSE
License-File: AUTHORS.rst
Requires-Dist: numpy
Requires-Dist: matplotlib
